[{
	"question": "How Alarm Annunciator indicates occurance of faults to the operator?",
	"answers": {
		"a": "Both b and c",
		"b": "Audio",
		"c": "Visual",
		"d": "None of these"
	},
	"correctAnswer": "a"
}, {
	"question": "The standard for annunciator is?",
	"answers": {
		"a": "ISA-18.1-1980 (R2004)",
		"b": "ISA-18.1-1978 (R2004)",
		"c": "ISA-18.1-1979 (R2004)",
		"d": "None of these"
	},
	"correctAnswer": "c"
}, {
	"question": "Which type of contacts used in Alarm Annunciator?",
	"answers": {
		"a": "Make to alarm (Normally open)",
		"b": "Both a and c",
		"c": "Break to alarm (Normally closed)",
		"d": "None of these"
	},
	"correctAnswer": "b"
}, {
	"question": "Alarm is notified when process parameter is crossing ?",
	"answers": {
		"a": "High set limit",
		"b": "Low set limit",
		"c": "In between high and Low",
		"d": "Both a and b"
	},
	"correctAnswer": "d"
}, {
	"question": "Acknowledge operation done in abnormal condition?",
	"answers": {
		"a": "Visual remains on",
		"b": "Audio alarm goes to silent",
		"c": "Ringback alarm goes to silent",
		"d": "All of these"
	},
	"correctAnswer": "d"
}]
